yy_mcp_get_weather/__init__.py
yy_mcp_get_weather/__main__.py
yy_mcp_get_weather/server.py
yy_mcp_get_weather-0.1.8.dist-info/METADATA
yy_mcp_get_weather-0.1.8.dist-info/WHEEL
yy_mcp_get_weather-0.1.8.dist-info/entry_points.txt
yy_mcp_get_weather-0.1.8.dist-info/top_level.txt
yy_mcp_get_weather-0.1.8.dist-info/RECORD
